{
  "started_at": "2026-06-12 14:35:08",
  "elapsed_seconds": 6386.8,
  "sources_total": 99,
  "sources_ok": 79,
  "sources_failed": 20,
  "keys_raw_total": 72834,
  "keys_unique_valid": 34500,
  "keys_duplicates": 21729,
  "keys_invalid": 969,
  "keys_insecure": 15636,
  "keys_unsupported": 0,
  "keys_whitelist_allowed": 9942,
  "keys_whitelist_rejected": 24558,
  "tested_best": 4,
  "tested_good": 7,
  "tested_slow": 79,
  "tested_bad": 9852,
  "publish_total": 11,
  "subscription_files": 1,
  "github_synced": true
}