{
  "started_at": "2026-05-14 06:44:08",
  "elapsed_seconds": 3623.2,
  "sources_total": 98,
  "sources_ok": 79,
  "sources_failed": 19,
  "keys_raw_total": 95940,
  "keys_unique_valid": 41967,
  "keys_duplicates": 36214,
  "keys_invalid": 1265,
  "keys_insecure": 16494,
  "keys_unsupported": 0,
  "keys_whitelist_allowed": 9021,
  "keys_whitelist_rejected": 32946,
  "tested_best": 2,
  "tested_good": 2,
  "tested_slow": 123,
  "tested_bad": 8894,
  "publish_total": 4,
  "subscription_files": 1,
  "github_synced": true
}