{
  "started_at": "2026-05-05 14:41:29",
  "elapsed_seconds": 5382.5,
  "sources_total": 98,
  "sources_ok": 76,
  "sources_failed": 22,
  "keys_raw_total": 100637,
  "keys_unique_valid": 40756,
  "keys_duplicates": 42733,
  "keys_invalid": 1205,
  "keys_insecure": 15943,
  "keys_unsupported": 0,
  "keys_whitelist_allowed": 8116,
  "keys_whitelist_rejected": 32640,
  "tested_best": 5,
  "tested_good": 52,
  "tested_slow": 181,
  "tested_bad": 7878,
  "publish_total": 57,
  "subscription_files": 1,
  "github_synced": true
}