{
  "started_at": "2026-04-13 01:58:43",
  "elapsed_seconds": 7660.6,
  "sources_total": 98,
  "sources_ok": 83,
  "sources_failed": 15,
  "keys_raw_total": 60574,
  "keys_unique_valid": 25506,
  "keys_duplicates": 23721,
  "keys_invalid": 934,
  "keys_insecure": 10413,
  "keys_unsupported": 0,
  "keys_whitelist_allowed": 9645,
  "keys_whitelist_rejected": 15861,
  "tested_best": 55,
  "tested_good": 23,
  "tested_slow": 225,
  "tested_bad": 9342,
  "publish_total": 78,
  "subscription_files": 1,
  "github_synced": true
}