{
  "started_at": "2026-06-26 09:50:01",
  "elapsed_seconds": 3556.9,
  "sources_total": 99,
  "sources_ok": 76,
  "sources_failed": 23,
  "keys_raw_total": 82710,
  "keys_unique_valid": 37082,
  "keys_duplicates": 26868,
  "keys_invalid": 948,
  "keys_insecure": 17812,
  "keys_unsupported": 0,
  "keys_whitelist_allowed": 8399,
  "keys_whitelist_rejected": 28683,
  "tested_best": 3,
  "tested_good": 2,
  "tested_slow": 243,
  "tested_bad": 8151,
  "publish_total": 5,
  "subscription_files": 1,
  "github_synced": true
}