{
  "started_at": "2026-04-07 20:51:09",
  "elapsed_seconds": 5770.6,
  "sources_total": 98,
  "sources_ok": 86,
  "sources_failed": 12,
  "keys_raw_total": 53046,
  "keys_unique_valid": 21885,
  "keys_duplicates": 20042,
  "keys_invalid": 945,
  "keys_insecure": 10174,
  "keys_unsupported": 0,
  "keys_whitelist_allowed": 9148,
  "keys_whitelist_rejected": 12737,
  "tested_best": 18,
  "tested_good": 9,
  "tested_slow": 209,
  "tested_bad": 8912,
  "publish_total": 27,
  "subscription_files": 1,
  "github_synced": true
}