{
  "started_at": "2026-06-22 18:49:42",
  "elapsed_seconds": 5117.7,
  "sources_total": 99,
  "sources_ok": 79,
  "sources_failed": 20,
  "keys_raw_total": 75160,
  "keys_unique_valid": 34969,
  "keys_duplicates": 21798,
  "keys_invalid": 985,
  "keys_insecure": 17408,
  "keys_unsupported": 0,
  "keys_whitelist_allowed": 7536,
  "keys_whitelist_rejected": 27433,
  "tested_best": 21,
  "tested_good": 5,
  "tested_slow": 91,
  "tested_bad": 7419,
  "publish_total": 26,
  "subscription_files": 1,
  "github_synced": true
}