{
  "started_at": "2026-05-07 08:17:28",
  "elapsed_seconds": 4190.2,
  "sources_total": 98,
  "sources_ok": 65,
  "sources_failed": 33,
  "keys_raw_total": 97729,
  "keys_unique_valid": 39107,
  "keys_duplicates": 42677,
  "keys_invalid": 1245,
  "keys_insecure": 14700,
  "keys_unsupported": 0,
  "keys_whitelist_allowed": 7236,
  "keys_whitelist_rejected": 31871,
  "tested_best": 9,
  "tested_good": 7,
  "tested_slow": 363,
  "tested_bad": 6857,
  "publish_total": 16,
  "subscription_files": 1,
  "github_synced": true
}