{
  "started_at": "2026-07-06 23:01:17",
  "elapsed_seconds": 3149.0,
  "sources_total": 108,
  "sources_ok": 82,
  "sources_failed": 26,
  "keys_raw_total": 82644,
  "keys_unique_valid": 40358,
  "keys_duplicates": 26307,
  "keys_invalid": 641,
  "keys_insecure": 15338,
  "keys_unsupported": 0,
  "keys_whitelist_allowed": 9897,
  "keys_whitelist_rejected": 30461,
  "tested_best": 51,
  "tested_good": 24,
  "tested_slow": 607,
  "tested_bad": 9215,
  "publish_total": 75,
  "subscription_files": 1,
  "github_synced": true
}