{
  "started_at": "2026-04-07 13:56:21",
  "elapsed_seconds": 4508.4,
  "sources_total": 98,
  "sources_ok": 87,
  "sources_failed": 11,
  "keys_raw_total": 52517,
  "keys_unique_valid": 22005,
  "keys_duplicates": 19492,
  "keys_invalid": 927,
  "keys_insecure": 10093,
  "keys_unsupported": 0,
  "keys_whitelist_allowed": 9233,
  "keys_whitelist_rejected": 12772,
  "tested_best": 17,
  "tested_good": 5,
  "tested_slow": 194,
  "tested_bad": 9017,
  "publish_total": 22,
  "subscription_files": 1,
  "github_synced": true
}