{
  "started_at": "2026-06-26 18:01:12",
  "elapsed_seconds": 3132.7,
  "sources_total": 99,
  "sources_ok": 76,
  "sources_failed": 23,
  "keys_raw_total": 81780,
  "keys_unique_valid": 37029,
  "keys_duplicates": 25854,
  "keys_invalid": 911,
  "keys_insecure": 17986,
  "keys_unsupported": 0,
  "keys_whitelist_allowed": 8286,
  "keys_whitelist_rejected": 28743,
  "tested_best": 158,
  "tested_good": 4,
  "tested_slow": 222,
  "tested_bad": 7902,
  "publish_total": 162,
  "subscription_files": 2,
  "github_synced": true
}