{
  "started_at": "2026-04-24 23:51:17",
  "elapsed_seconds": 5937.8,
  "sources_total": 98,
  "sources_ok": 79,
  "sources_failed": 19,
  "keys_raw_total": 81106,
  "keys_unique_valid": 32594,
  "keys_duplicates": 31450,
  "keys_invalid": 1394,
  "keys_insecure": 15668,
  "keys_unsupported": 0,
  "keys_whitelist_allowed": 8763,
  "keys_whitelist_rejected": 23831,
  "tested_best": 39,
  "tested_good": 14,
  "tested_slow": 245,
  "tested_bad": 8465,
  "publish_total": 53,
  "subscription_files": 1,
  "github_synced": true
}