{
  "started_at": "2026-06-10 20:21:22",
  "elapsed_seconds": 4061.5,
  "sources_total": 99,
  "sources_ok": 79,
  "sources_failed": 20,
  "keys_raw_total": 72631,
  "keys_unique_valid": 33962,
  "keys_duplicates": 21183,
  "keys_invalid": 865,
  "keys_insecure": 16621,
  "keys_unsupported": 0,
  "keys_whitelist_allowed": 9352,
  "keys_whitelist_rejected": 24610,
  "tested_best": 20,
  "tested_good": 11,
  "tested_slow": 68,
  "tested_bad": 9253,
  "publish_total": 31,
  "subscription_files": 1,
  "github_synced": true
}