{
  "started_at": "2026-05-15 20:24:07",
  "elapsed_seconds": 3518.8,
  "sources_total": 98,
  "sources_ok": 79,
  "sources_failed": 19,
  "keys_raw_total": 92496,
  "keys_unique_valid": 41439,
  "keys_duplicates": 33212,
  "keys_invalid": 1266,
  "keys_insecure": 16579,
  "keys_unsupported": 0,
  "keys_whitelist_allowed": 8395,
  "keys_whitelist_rejected": 33044,
  "tested_best": 2,
  "tested_good": 1,
  "tested_slow": 49,
  "tested_bad": 8343,
  "publish_total": 3,
  "subscription_files": 1,
  "github_synced": true
}