{
  "started_at": "2026-04-03 10:00:34",
  "elapsed_seconds": 3015.8,
  "sources_total": 98,
  "sources_ok": 86,
  "sources_failed": 12,
  "keys_raw_total": 52954,
  "keys_unique_valid": 20675,
  "keys_duplicates": 21595,
  "keys_invalid": 967,
  "keys_insecure": 9717,
  "keys_unsupported": 0,
  "keys_whitelist_allowed": 8607,
  "keys_whitelist_rejected": 12068,
  "tested_best": 44,
  "tested_good": 122,
  "tested_slow": 179,
  "tested_bad": 8262,
  "publish_total": 166,
  "subscription_files": 2,
  "github_synced": true
}